PyPlotJuggling/__init__.py
pyplotjuggling-1.0.2.dist-info/licenses/LICENSE
pyplotjuggling-1.0.2.dist-info/METADATA
pyplotjuggling-1.0.2.dist-info/WHEEL
pyplotjuggling-1.0.2.dist-info/top_level.txt
pyplotjuggling-1.0.2.dist-info/RECORD
